{
  "__inputs": [
    {
      "name": "DS_PROMETHEUS",
      "label": "Prometheus",
      "description": "",
      "type": "datasource",
      "pluginId": "prometheus",
      "pluginName": "Prometheus"
    }
  ],
  "__elements": {},
  "__requires": [
    {
      "type": "grafana",
      "id": "grafana",
      "name": "Grafana",
      "version": "9.3.6"
    },
    {
      "type": "panel",
      "id": "graph",
      "name": "Graph (old)",
      "version": ""
    },
    {
      "type": "datasource",
      "id": "prometheus",
      "name": "Prometheus",
      "version": "1.0.0"
    },
    {
      "type": "panel",
      "id": "stat",
      "name": "Stat",
      "version": ""
    },
    {
      "type": "panel",
      "id": "table",
      "name": "Table",
      "version": ""
    },
    {
      "type": "panel",
      "id": "timeseries",
      "name": "Time series",
      "version": ""
    }
  ],
  "annotations": {
    "list": [
      {
        "builtIn": 1,
        "datasource": {
          "type": "datasource",
          "uid": "grafana"
        },
        "enable": true,
        "hide": true,
        "iconColor": "rgba(0, 211, 255, 1)",
        "name": "Annotations & Alerts",
        "target": {
          "limit": 100,
          "matchAny": false,
          "tags": [],
          "type": "dashboard"
        },
        "type": "dashboard"
      }
    ]
  },
  "editable": true,
  "fiscalYearStartMonth": 0,
  "graphTooltip": 1,
  "id": null,
  "links": [],
  "liveNow": false,
  "panels": [
    {
      "datasource": {
        "type": "prometheus",
        "uid": "${DS_PROMETHEUS}"
      },
      "fieldConfig": {
        "defaults": {
          "color": {
            "mode": "palette-classic"
          },
          "custom": {
            "axisCenteredZero": false,
            "axisColorMode": "text",
            "axisLabel": "",
            "axisPlacement": "auto",
            "barAlignment": 0,
            "drawStyle": "line",
            "fillOpacity": 10,
            "gradientMode": "none",
            "hideFrom": {
              "legend": false,
              "tooltip": false,
              "viz": false
            },
            "lineInterpolation": "linear",
            "lineWidth": 1,
            "pointSize": 5,
            "scaleDistribution": {
              "type": "linear"
            },
            "showPoints": "never",
            "spanNulls": false,
            "stacking": {
              "group": "A",
              "mode": "none"
            },
            "thresholdsStyle": {
              "mode": "off"
            }
          },
          "mappings": [],
          "min": 0,
          "thresholds": {
            "mode": "absolute",
            "steps": [
              {
                "color": "green",
                "value": null
              },
              {
                "color": "red",
                "value": 80
              }
            ]
          },
          "unit": "short"
        },
        "overrides": []
      },
      "gridPos": {
        "h": 7,
        "w": 12,
        "x": 0,
        "y": 0
      },
      "id": 11,
      "options": {
        "legend": {
          "calcs": [],
          "displayMode": "list",
          "placement": "bottom",
          "showLegend": true
        },
        "tooltip": {
          "mode": "multi",
          "sort": "none"
        }
      },
      "pluginVersion": "",
      "targets": [
        {
          "datasource": {
            "type": "prometheus",
            "uid": "${DS_PROMETHEUS}"
          },
          "editorMode": "code",
          "exemplar": true,
          "expr": "sum by([[aggr_criteria]] , redpanda_group) (max by(redpanda_namespace, redpanda_topic, redpanda_partition)(redpanda_kafka_max_offset{redpanda_namespace=\"kafka\", redpanda_topic=~\"[[redpanda_topic]]\"}) - on(redpanda_topic, redpanda_partition) group_right max by(redpanda_group, redpanda_topic, redpanda_partition)(redpanda_kafka_consumer_group_committed_offset{redpanda_group=~\"[[redpanda_group]]\"}) +1)",
          "interval": "",
          "legendFormat": "Group: {{redpanda_group}}, Topic: {{redpanda_topic}}, Partition: {{redpanda_partition}}",
          "range": true,
          "refId": "A"
        }
      ],
      "title": "Consumer Group Offset Lag",
      "type": "timeseries"
    },
    {
      "datasource": {
        "type": "prometheus",
        "uid": "${DS_PROMETHEUS}"
      },
      "fieldConfig": {
        "defaults": {
          "color": {
            "mode": "thresholds"
          },
          "mappings": [],
          "thresholds": {
            "mode": "absolute",
            "steps": [
              {
                "color": "green",
                "value": null
              },
              {
                "color": "red",
                "value": 80
              }
            ]
          }
        },
        "overrides": []
      },
      "gridPos": {
        "h": 7,
        "w": 3,
        "x": 12,
        "y": 0
      },
      "id": 19,
      "options": {
        "colorMode": "value",
        "graphMode": "none",
        "justifyMode": "auto",
        "orientation": "auto",
        "reduceOptions": {
          "calcs": [
            "lastNotNull"
          ],
          "fields": "",
          "values": false
        },
        "textMode": "auto"
      },
      "pluginVersion": "9.3.6",
      "targets": [
        {
          "datasource": {
            "type": "prometheus",
            "uid": "${DS_PROMETHEUS}"
          },
          "expr": "count(count by(redpanda_group)(redpanda_kafka_consumer_group_committed_offset{redpanda_topic=~\"[[redpanda_topic]]\", redpanda_group=~\"[[redpanda_group]]\", redpanda_cloud_data_cluster_name=~\"[[data_cluster]]\"}))",
          "refId": "A"
        }
      ],
      "title": "Consumer Groups",
      "type": "stat"
    },
    {
      "datasource": {
        "type": "prometheus",
        "uid": "${DS_PROMETHEUS}"
      },
      "fieldConfig": {
        "defaults": {
          "color": {
            "mode": "thresholds"
          },
          "mappings": [],
          "min": 0,
          "thresholds": {
            "mode": "percentage",
            "steps": [
              {
                "color": "green",
                "value": null
              }
            ]
          },
          "unit": "short"
        },
        "overrides": []
      },
      "gridPos": {
        "h": 7,
        "w": 3,
        "x": 15,
        "y": 0
      },
      "id": 23,
      "options": {
        "colorMode": "value",
        "graphMode": "area",
        "justifyMode": "auto",
        "orientation": "auto",
        "reduceOptions": {
          "calcs": [
            "lastNotNull"
          ],
          "fields": "",
          "values": false
        },
        "textMode": "auto"
      },
      "pluginVersion": "9.3.6",
      "targets": [
        {
          "datasource": {
            "type": "prometheus",
            "uid": "${DS_PROMETHEUS}"
          },
          "editorMode": "code",
          "exemplar": true,
          "expr": "count(count(redpanda_kafka_max_offset{redpanda_topic=~\"[[redpanda_topic]]\",redpanda_cloud_data_cluster_name=~\"[[data_cluster]]\"}) by (redpanda_topic, redpanda_partition))",
          "interval": "",
          "legendFormat": "group: {{group}}, redpanda_topic: {{redpanda_topic}}, partition: {{partition}}",
          "range": true,
          "refId": "A"
        }
      ],
      "title": "Partitions",
      "type": "stat"
    },
    {
      "datasource": {
        "type": "prometheus",
        "uid": "${DS_PROMETHEUS}"
      },
      "fieldConfig": {
        "defaults": {
          "color": {
            "mode": "thresholds"
          },
          "mappings": [],
          "min": 0,
          "thresholds": {
            "mode": "percentage",
            "steps": [
              {
                "color": "green",
                "value": null
              },
              {
                "color": "red",
                "value": 80
              }
            ]
          },
          "unit": "short"
        },
        "overrides": []
      },
      "gridPos": {
        "h": 7,
        "w": 3,
        "x": 18,
        "y": 0
      },
      "id": 25,
      "options": {
        "colorMode": "value",
        "graphMode": "area",
        "justifyMode": "auto",
        "orientation": "auto",
        "reduceOptions": {
          "calcs": [
            "lastNotNull"
          ],
          "fields": "",
          "values": false
        },
        "textMode": "auto"
      },
      "pluginVersion": "9.3.6",
      "targets": [
        {
          "datasource": {
            "type": "prometheus",
            "uid": "${DS_PROMETHEUS}"
          },
          "editorMode": "code",
          "exemplar": true,
          "expr": "sum(max by(redpanda_namespace, redpanda_topic, redpanda_partition)(redpanda_kafka_max_offset{redpanda_namespace=\"kafka\", redpanda_topic=~\"[[redpanda_topic]]\",redpanda_cloud_data_cluster_name=~\"[[data_cluster]]\"}) - on(redpanda_topic, redpanda_partition) group_right max by(redpanda_group, redpanda_topic, redpanda_partition)(redpanda_kafka_consumer_group_committed_offset{redpanda_group=~\"[[redpanda_group]]\", redpanda_topic=~\"[[redpanda_topic]]\",redpanda_cloud_data_cluster_name=~\"[[data_cluster]]\"}) + 1)",
          "interval": "",
          "legendFormat": "group: {{group}}, redpanda_topic: {{redpanda_topic}}, partition: {{partition}}",
          "range": true,
          "refId": "A"
        }
      ],
      "title": "Consumer Group Offset Lag",
      "type": "stat"
    },
    {
      "datasource": {
        "type": "prometheus",
        "uid": "${DS_PROMETHEUS}"
      },
      "description": "Only applies when topics are being written to (to understand the write-rate and compute the offset against that)",
      "fieldConfig": {
        "defaults": {
          "color": {
            "mode": "thresholds"
          },
          "mappings": [],
          "min": 0,
          "thresholds": {
            "mode": "percentage",
            "steps": [
              {
                "color": "green",
                "value": null
              },
              {
                "color": "red",
                "value": 80
              }
            ]
          },
          "unit": "s"
        },
        "overrides": []
      },
      "gridPos": {
        "h": 7,
        "w": 3,
        "x": 21,
        "y": 0
      },
      "id": 24,
      "options": {
        "colorMode": "value",
        "graphMode": "area",
        "justifyMode": "auto",
        "orientation": "auto",
        "reduceOptions": {
          "calcs": [
            "lastNotNull"
          ],
          "fields": "",
          "values": false
        },
        "textMode": "auto"
      },
      "pluginVersion": "9.3.6",
      "targets": [
        {
          "datasource": {
            "type": "prometheus",
            "uid": "${DS_PROMETHEUS}"
          },
          "editorMode": "code",
          "exemplar": true,
          "expr": "avg\n(\n    (max by(redpanda_namespace, redpanda_topic, redpanda_partition)(redpanda_kafka_max_offset{redpanda_namespace=\"kafka\", redpanda_topic!=\"__consumer_offsets\"}) - on (redpanda_topic, redpanda_partition) group_right max by(redpanda_group,redpanda_topic, redpanda_partition) (redpanda_kafka_consumer_group_committed_offset{redpanda_group=~\"[[redpanda_group]]\",redpanda_topic=~\"[[redpanda_topic]]\",redpanda_cloud_data_cluster_name=~\"[[data_cluster]]\"})\n    )\n    / on (redpanda_topic, redpanda_partition) group_right\n    max by(redpanda_namespace, redpanda_topic, redpanda_partition) (rate(redpanda_kafka_max_offset{redpanda_topic=~\"[[redpanda_topic]]\",redpanda_cloud_data_cluster_name=~\"[[data_cluster]]\"}[$__rate_interval])!=0) \n)",
          "interval": "",
          "legendFormat": "group: {{group}}, redpanda_topic: {{redpanda_topic}}, partition: {{partition}}",
          "range": true,
          "refId": "A"
        }
      ],
      "title": "Offset Lag (time)",
      "type": "stat"
    },
    {
      "datasource": {
        "type": "prometheus",
        "uid": "${DS_PROMETHEUS}"
      },
      "fieldConfig": {
        "defaults": {
          "color": {
            "mode": "thresholds"
          },
          "custom": {
            "align": "auto",
            "displayMode": "auto",
            "filterable": false,
            "inspect": false
          },
          "mappings": [],
          "min": 0,
          "thresholds": {
            "mode": "absolute",
            "steps": [
              {
                "color": "green",
                "value": null
              },
              {
                "color": "red",
                "value": 80
              }
            ]
          },
          "unit": "short"
        },
        "overrides": [
          {
            "matcher": {
              "id": "byName",
              "options": "partition"
            },
            "properties": [
              {
                "id": "custom.width",
                "value": 79
              }
            ]
          },
          {
            "matcher": {
              "id": "byName",
              "options": "group"
            },
            "properties": [
              {
                "id": "custom.width",
                "value": 166
              }
            ]
          },
          {
            "matcher": {
              "id": "byName",
              "options": "redpanda_topic"
            },
            "properties": [
              {
                "id": "custom.width",
                "value": 128
              }
            ]
          },
          {
            "matcher": {
              "id": "byName",
              "options": "Value"
            },
            "properties": [
              {
                "id": "custom.width",
                "value": 52
              }
            ]
          },
          {
            "matcher": {
              "id": "byName",
              "options": "redpanda_partition"
            },
            "properties": [
              {
                "id": "custom.width",
                "value": 110
              }
            ]
          },
          {
            "matcher": {
              "id": "byName",
              "options": "redpanda_group"
            },
            "properties": [
              {
                "id": "custom.width",
                "value": 117
              }
            ]
          },
          {
            "matcher": {
              "id": "byName",
              "options": "Lag"
            },
            "properties": [
              {
                "id": "custom.width",
                "value": 140
              }
            ]
          }
        ]
      },
      "gridPos": {
        "h": 8,
        "w": 7,
        "x": 0,
        "y": 7
      },
      "id": 15,
      "options": {
        "footer": {
          "enablePagination": false,
          "fields": "",
          "reducer": [
            "sum"
          ],
          "show": false
        },
        "showHeader": true,
        "sortBy": []
      },
      "pluginVersion": "9.3.6",
      "targets": [
        {
          "datasource": {
            "type": "prometheus",
            "uid": "${DS_PROMETHEUS}"
          },
          "editorMode": "code",
          "exemplar": false,
          "expr": "sum by([[aggr_criteria]] , redpanda_group) (max by(redpanda_namespace, redpanda_topic, redpanda_partition)(redpanda_kafka_max_offset{redpanda_namespace=\"kafka\", redpanda_topic=~\"[[redpanda_topic]]\"}) - on(redpanda_topic, redpanda_partition) group_right max by(redpanda_group, redpanda_topic, redpanda_partition)(redpanda_kafka_consumer_group_committed_offset{redpanda_group=~\"[[redpanda_group]]\"}) +1)",
          "format": "table",
          "instant": true,
          "interval": "",
          "legendFormat": "__auto",
          "range": false,
          "refId": "A"
        }
      ],
      "title": "Consumer Group Offset Lag",
      "transformations": [
        {
          "id": "organize",
          "options": {
            "excludeByName": {
              "Time": true,
              "instance": true,
              "job": true,
              "shard": true
            },
            "indexByName": {
              "Time": 1,
              "Value": 4,
              "redpanda_group": 2,
              "redpanda_partition": 3,
              "redpanda_topic": 0
            },
            "renameByName": {
              "Value": "Lag",
              "redpanda_group": "Group",
              "redpanda_partition": "Partition",
              "redpanda_topic": "Topic"
            }
          }
        }
      ],
      "type": "table"
    },
    {
      "datasource": {
        "type": "prometheus",
        "uid": "${DS_PROMETHEUS}"
      },
      "fieldConfig": {
        "defaults": {
          "color": {
            "mode": "thresholds"
          },
          "custom": {
            "align": "auto",
            "displayMode": "auto",
            "inspect": false
          },
          "mappings": [],
          "thresholds": {
            "mode": "absolute",
            "steps": [
              {
                "color": "green",
                "value": null
              },
              {
                "color": "red",
                "value": 80
              }
            ]
          }
        },
        "overrides": [
          {
            "matcher": {
              "id": "byName",
              "options": "Value"
            },
            "properties": [
              {
                "id": "custom.width",
                "value": 73
              }
            ]
          },
          {
            "matcher": {
              "id": "byName",
              "options": "Group"
            },
            "properties": [
              {
                "id": "custom.width",
                "value": 146
              }
            ]
          },
          {
            "matcher": {
              "id": "byName",
              "options": "Topic"
            },
            "properties": [
              {
                "id": "custom.width",
                "value": 135
              }
            ]
          },
          {
            "matcher": {
              "id": "byName",
              "options": "Consumption Rate"
            },
            "properties": [
              {
                "id": "custom.width",
                "value": 104
              }
            ]
          }
        ]
      },
      "gridPos": {
        "h": 8,
        "w": 7,
        "x": 7,
        "y": 7
      },
      "id": 22,
      "options": {
        "footer": {
          "fields": "",
          "reducer": [
            "sum"
          ],
          "show": false
        },
        "showHeader": true,
        "sortBy": []
      },
      "pluginVersion": "9.3.6",
      "targets": [
        {
          "datasource": {
            "type": "prometheus",
            "uid": "${DS_PROMETHEUS}"
          },
          "editorMode": "code",
          "exemplar": false,
          "expr": "sum by(redpanda_group, redpanda_topic) (rate(redpanda_kafka_consumer_group_committed_offset{redpanda_topic=~\"[[redpanda_topic]]\", redpanda_group=~\"[[redpanda_group]]\", redpanda_cloud_data_cluster_name=~\"[[data_cluster]]\"}[1m]))",
          "format": "table",
          "instant": true,
          "legendFormat": "Group: {{redpanda_group}}",
          "range": false,
          "refId": "A"
        }
      ],
      "title": "Topic Consumption Rate by Group",
      "transformations": [
        {
          "id": "organize",
          "options": {
            "excludeByName": {
              "Time": true
            },
            "indexByName": {},
            "renameByName": {
              "Value": "Consumption Rate",
              "redpanda_group": "Group",
              "redpanda_topic": "Topic"
            }
          }
        }
      ],
      "type": "table"
    },
    {
      "datasource": {
        "type": "prometheus",
        "uid": "${DS_PROMETHEUS}"
      },
      "fieldConfig": {
        "defaults": {
          "color": {
            "mode": "palette-classic"
          },
          "custom": {
            "axisCenteredZero": false,
            "axisColorMode": "text",
            "axisLabel": "",
            "axisPlacement": "auto",
            "barAlignment": 0,
            "drawStyle": "line",
            "fillOpacity": 0,
            "gradientMode": "none",
            "hideFrom": {
              "legend": false,
              "tooltip": false,
              "viz": false
            },
            "lineInterpolation": "linear",
            "lineStyle": {
              "fill": "solid"
            },
            "lineWidth": 1,
            "pointSize": 5,
            "scaleDistribution": {
              "type": "linear"
            },
            "showPoints": "never",
            "spanNulls": false,
            "stacking": {
              "group": "A",
              "mode": "normal"
            },
            "thresholdsStyle": {
              "mode": "off"
            }
          },
          "mappings": [],
          "thresholds": {
            "mode": "absolute",
            "steps": [
              {
                "color": "green",
                "value": null
              },
              {
                "color": "red",
                "value": 80
              }
            ]
          }
        },
        "overrides": []
      },
      "gridPos": {
        "h": 8,
        "w": 5,
        "x": 14,
        "y": 7
      },
      "id": 20,
      "options": {
        "legend": {
          "calcs": [],
          "displayMode": "list",
          "placement": "bottom",
          "showLegend": true
        },
        "tooltip": {
          "mode": "single",
          "sort": "none"
        }
      },
      "targets": [
        {
          "datasource": {
            "type": "prometheus",
            "uid": "${DS_PROMETHEUS}"
          },
          "editorMode": "code",
          "expr": "sum by([[aggr_criteria]] ) (rate(redpanda_kafka_max_offset{redpanda_topic=~\"[[redpanda_topic]]\",redpanda_cloud_data_cluster_name=~\"[[data_cluster]]\"}[$__rate_interval]))",
          "legendFormat": "Topic: {{redpanda_topic}}, Partition: {{redpanda_partition}}",
          "range": true,
          "refId": "A"
        }
      ],
      "title": "Topic Production Rate",
      "type": "timeseries"
    },
    {
      "datasource": {
        "type": "prometheus",
        "uid": "${DS_PROMETHEUS}"
      },
      "fieldConfig": {
        "defaults": {
          "color": {
            "mode": "palette-classic"
          },
          "custom": {
            "axisCenteredZero": false,
            "axisColorMode": "text",
            "axisLabel": "",
            "axisPlacement": "auto",
            "barAlignment": 0,
            "drawStyle": "line",
            "fillOpacity": 0,
            "gradientMode": "none",
            "hideFrom": {
              "legend": false,
              "tooltip": false,
              "viz": false
            },
            "lineInterpolation": "linear",
            "lineWidth": 1,
            "pointSize": 5,
            "scaleDistribution": {
              "type": "linear"
            },
            "showPoints": "never",
            "spanNulls": false,
            "stacking": {
              "group": "A",
              "mode": "none"
            },
            "thresholdsStyle": {
              "mode": "off"
            }
          },
          "mappings": [],
          "thresholds": {
            "mode": "absolute",
            "steps": [
              {
                "color": "green",
                "value": null
              },
              {
                "color": "red",
                "value": 80
              }
            ]
          }
        },
        "overrides": []
      },
      "gridPos": {
        "h": 8,
        "w": 5,
        "x": 19,
        "y": 7
      },
      "id": 17,
      "options": {
        "legend": {
          "calcs": [],
          "displayMode": "list",
          "placement": "bottom",
          "showLegend": true
        },
        "tooltip": {
          "mode": "single",
          "sort": "none"
        }
      },
      "targets": [
        {
          "datasource": {
            "type": "prometheus",
            "uid": "${DS_PROMETHEUS}"
          },
          "editorMode": "code",
          "expr": "sum by([[aggr_criteria]], redpanda_group ) (rate(redpanda_kafka_consumer_group_committed_offset{redpanda_cloud_data_cluster_name=~\"[[data_cluster]]\"}[$__rate_interval]))",
          "legendFormat": "group: {{redpanda_group}}, topic: {{redpanda_topic}}, partition: {{redpanda_partition}}",
          "range": true,
          "refId": "A"
        }
      ],
      "title": "Topic Consumption Rate by Group",
      "type": "timeseries"
    },
    {
      "aliasColors": {},
      "bars": false,
      "dashLength": 10,
      "dashes": false,
      "datasource": {
        "type": "prometheus",
        "uid": "${DS_PROMETHEUS}"
      },
      "fill": 1,
      "fillGradient": 0,
      "gridPos": {
        "h": 8,
        "w": 12,
        "x": 0,
        "y": 15
      },
      "hiddenSeries": false,
      "id": 2,
      "legend": {
        "avg": false,
        "current": false,
        "max": false,
        "min": false,
        "show": true,
        "total": false,
        "values": false
      },
      "lines": true,
      "linewidth": 1,
      "nullPointMode": "null",
      "options": {
        "alertThreshold": true
      },
      "percentage": false,
      "pluginVersion": "9.3.6",
      "pointradius": 2,
      "points": false,
      "renderer": "flot",
      "seriesOverrides": [],
      "spaceLength": 10,
      "stack": false,
      "steppedLine": false,
      "targets": [
        {
          "datasource": {
            "type": "prometheus",
            "uid": "${DS_PROMETHEUS}"
          },
          "editorMode": "code",
          "exemplar": true,
          "expr": "max by([[aggr_criteria]]) (rate(redpanda_kafka_max_offset{redpanda_topic=~\"[[redpanda_topic]]\", redpanda_cloud_data_cluster_name=~\"[[data_cluster]]\"}[$__rate_interval]))",
          "interval": "",
          "legendFormat": "Topic: {{redpanda_topic}}, Partition: {{redpanda_partition}}",
          "range": true,
          "refId": "A"
        }
      ],
      "thresholds": [],
      "timeRegions": [],
      "title": "Log End Offset Rate",
      "tooltip": {
        "shared": true,
        "sort": 0,
        "value_type": "individual"
      },
      "type": "graph",
      "xaxis": {
        "mode": "time",
        "show": true,
        "values": []
      },
      "yaxes": [
        {
          "$$hashKey": "object:24",
          "format": "short",
          "logBase": 1,
          "show": true
        },
        {
          "$$hashKey": "object:25",
          "format": "short",
          "logBase": 1,
          "show": true
        }
      ],
      "yaxis": {
        "align": false
      }
    },
    {
      "datasource": {
        "type": "prometheus",
        "uid": "${DS_PROMETHEUS}"
      },
      "fieldConfig": {
        "defaults": {
          "color": {
            "mode": "palette-classic"
          },
          "custom": {
            "axisCenteredZero": false,
            "axisColorMode": "text",
            "axisLabel": "",
            "axisPlacement": "auto",
            "barAlignment": 0,
            "drawStyle": "line",
            "fillOpacity": 10,
            "gradientMode": "none",
            "hideFrom": {
              "legend": false,
              "tooltip": false,
              "viz": false
            },
            "lineInterpolation": "linear",
            "lineWidth": 1,
            "pointSize": 5,
            "scaleDistribution": {
              "type": "linear"
            },
            "showPoints": "never",
            "spanNulls": false,
            "stacking": {
              "group": "A",
              "mode": "normal"
            },
            "thresholdsStyle": {
              "mode": "off"
            }
          },
          "mappings": [],
          "thresholds": {
            "mode": "absolute",
            "steps": [
              {
                "color": "green",
                "value": null
              },
              {
                "color": "red",
                "value": 80
              }
            ]
          },
          "unit": "short"
        },
        "overrides": []
      },
      "gridPos": {
        "h": 8,
        "w": 12,
        "x": 12,
        "y": 15
      },
      "id": 3,
      "options": {
        "legend": {
          "calcs": [],
          "displayMode": "list",
          "placement": "bottom",
          "showLegend": true
        },
        "tooltip": {
          "mode": "multi",
          "sort": "none"
        }
      },
      "pluginVersion": "",
      "targets": [
        {
          "datasource": {
            "type": "prometheus",
            "uid": "${DS_PROMETHEUS}"
          },
          "editorMode": "builder",
          "exemplar": true,
          "expr": "max by([[aggr_criteria]], redpanda_group) (rate(redpanda_kafka_consumer_group_committed_offset{redpanda_topic=~\"[[redpanda_topic]]\", redpanda_group=~\"[[redpanda_group]]\", redpanda_cloud_data_cluster_name=~\"[[data_cluster]]\"}[$__rate_interval]))",
          "interval": "",
          "legendFormat": "Group: {{redpanda_group}}, Topic: {{redpanda_topic}}, Partition: {{redpanda_partition}}",
          "range": true,
          "refId": "A"
        }
      ],
      "title": "Consumer Group Offsets Rate",
      "type": "timeseries"
    }
  ],
  "refresh": "30s",
  "schemaVersion": 37,
  "style": "dark",
  "tags": [],
  "templating": {
    "list": [
      {
        "current": {
          "selected": false,
          "text": "Prometheus",
          "value": "Prometheus"
        },
        "hide": 0,
        "includeAll": false,
        "label": "Data Source",
        "multi": false,
        "name": "DS_PROMETHEUS",
        "options": [],
        "query": "prometheus",
        "refresh": 1,
        "regex": "",
        "skipUrlSync": false,
        "type": "datasource"
      },
      {
        "allValue": "",
        "current": {},
        "datasource": {
          "type": "prometheus",
          "uid": "${DS_PROMETHEUS}"
        },
        "definition": "label_values(redpanda_kafka_consumer_group_topics{redpanda_topic !~ 'controller|group|__consumer_offsets'}, redpanda_group)",
        "hide": 0,
        "includeAll": true,
        "label": "Group",
        "multi": true,
        "name": "redpanda_group",
        "options": [],
        "query": {
          "query": "label_values(redpanda_kafka_consumer_group_topics{redpanda_topic !~ 'controller|group|__consumer_offsets'}, redpanda_group)",
          "refId": "StandardVariableQuery"
        },
        "refresh": 2,
        "regex": "",
        "skipUrlSync": false,
        "sort": 0,
        "tagValuesQuery": "",
        "tagsQuery": "",
        "type": "query",
        "useTags": false
      },
      {
        "allValue": "",
        "current": {},
        "datasource": {
          "type": "prometheus",
          "uid": "${DS_PROMETHEUS}"
        },
        "definition": "label_values(redpanda_kafka_replicas{redpanda_topic !~ 'controller|group|__consumer_offsets', redpanda_namespace=\"kafka\"}, redpanda_topic)",
        "hide": 0,
        "includeAll": true,
        "label": "Topic",
        "multi": true,
        "name": "redpanda_topic",
        "options": [],
        "query": {
          "query": "label_values(redpanda_kafka_replicas{redpanda_topic !~ 'controller|group|__consumer_offsets', redpanda_namespace=\"kafka\"}, redpanda_topic)",
          "refId": "StandardVariableQuery"
        },
        "refresh": 2,
        "regex": "",
        "skipUrlSync": false,
        "sort": 0,
        "tagValuesQuery": "",
        "tagsQuery": "",
        "type": "query",
        "useTags": false
      },
      {
        "current": {
          "selected": true,
          "text": "Topic",
          "value": "redpanda_topic"
        },
        "hide": 0,
        "includeAll": false,
        "label": "Aggregate by",
        "multi": false,
        "name": "aggr_criteria",
        "options": [
          {
            "selected": true,
            "text": "Topic",
            "value": "redpanda_topic"
          },
          {
            "selected": false,
            "text": "Topic,Partition",
            "value": "redpanda_topic,redpanda_partition"
          }
        ],
        "query": "Topic : redpanda_topic,Topic\\,Partition : redpanda_topic\\,redpanda_partition",
        "queryValue": "",
        "skipUrlSync": false,
        "type": "custom"
      },
      {
        "current": {},
        "datasource": {
          "type": "prometheus",
          "uid": "${DS_PROMETHEUS}"
        },
        "definition": "label_values(redpanda_cloud_data_cluster_name)",
        "hide": 0,
        "includeAll": false,
        "label": "Data cluster",
        "multi": false,
        "name": "data_cluster",
        "options": [],
        "query": {
          "query": "label_values(redpanda_cloud_data_cluster_name)",
          "refId": "StandardVariableQuery"
        },
        "refresh": 1,
        "regex": "",
        "skipUrlSync": false,
        "sort": 0,
        "type": "query"
      },
      {
        "datasource": {
          "type": "prometheus",
          "uid": "${DS_PROMETHEUS}"
        },
        "filters": [],
        "hide": 0,
        "name": "Filters",
        "skipUrlSync": false,
        "type": "adhoc"
      }
    ]
  },
  "time": {
    "from": "now-30m",
    "to": "now"
  },
  "timepicker": {},
  "timezone": "",
  "title": "Kafka Consumer Offsets",
  "uid": "rtW0EDenk",
  "version": 1,
  "weekStart": ""
}
